scrippy-1.0.8.data/scripts/scrippy
scrippy_installer/__init__.py
scrippy_installer/error/__init__.py
scrippy_installer/installer/__init__.py
scrippy_installer/logger/__init__.py
scrippy-1.0.8.dist-info/LICENSE
scrippy-1.0.8.dist-info/METADATA
scrippy-1.0.8.dist-info/WHEEL
scrippy-1.0.8.dist-info/top_level.txt
scrippy-1.0.8.dist-info/RECORD
